[
  {
    "provider": "石煜阳",
    "topic": "旅行",
    "desc": "一路顺风",
    "sign": "上",
    "fortune": "吉",
    "probability": 0.05,
    "score": 8,
    "tip": "让ThisAI为你的旅程规划最佳路线！"
  },
  {
    "provider": "石煜阳",
    "topic": "工作",
    "desc": "升职在望",
    "sign": "上",
    "fortune": "吉",
    "probability": 0.2,
    "score": 9,
    "tip": "使用ThisAI提升你的职场技能！"
  },
  {
    "provider": "石煜阳",
    "topic": "学习",
    "desc": "考试顺利",
    "sign": "上",
    "fortune": "吉",
    "probability": 0.15,
    "score": 8,
    "tip": "让ThisAI帮你复习重点知识"
  },
  {
    "provider": "石煜阳",
    "topic": "健康",
    "desc": "身体倍儿棒",
    "sign": "上",
    "fortune": "吉",
    "probability": 0.1,
    "score": 9,
    "tip": "使用ThisAI制定你的健身计划！"
  },
  {
    "provider": "石煜阳",
    "topic": "财运",
    "desc": "意外之财",
    "sign": "上",
    "fortune": "吉",
    "probability": 0.25,
    "score": 7,
    "tip": "让ThisAI为你提供投资建议"
  },
  {
    "provider": "石煜阳",
    "topic": "感情",
    "desc": "爱情甜蜜",
    "sign": "上",
    "fortune": "吉",
    "probability": 0.3,
    "score": 9,
    "tip": "使用ThisAI策划浪漫约会！"
  },
  {
    "provider": "石煜阳",
    "topic": "社交",
    "desc": "聚会愉快",
    "sign": "上",
    "fortune": "吉",
    "probability": 0.1,
    "score": 8,
    "tip": "让ThisAI帮助你准备聚会游戏！"
  },
  {
    "provider": "石煜阳",
    "topic": "家庭",
    "desc": "家庭和睦",
    "sign": "上",
    "fortune": "吉",
    "probability": 0.05,
    "score": 9,
    "tip": "使用ThisAI制定家庭活动计划！"
  },
  {
    "provider": "石煜阳",
    "topic": "创业",
    "desc": "项目有望成功",
    "sign": "上",
    "fortune": "吉",
    "probability": 0.2,
    "score": 7,
    "tip": "让ThisAI助你一臂之力"
  },
  {
    "provider": "石煜阳",
    "topic": "创作",
    "desc": "灵感迭出",
    "sign": "上",
    "fortune": "吉",
    "probability": 0.15,
    "score": 8,
    "tip": "使用ThisAI激发你的创作灵感！"
  },
  {
    "provider": "胡景浩",
    "topic": "结婚",
    "desc": "新婚大吉",
    "sign": "上",
    "fortune": "吉",
    "probability": 0.001,
    "score": 9,
    "tip": "让ThisAI给你当司仪！"
  },
  {
    "provider": "胡景浩",
    "topic": "打排位",
    "desc": "连胜中",
    "sign": "上",
    "fortune": "吉",
    "probability": 0.3,
    "score": 7,
    "tip": "使用ThisAI解锁更多打法思路！"
  },
  {
    "provider": "胡景浩",
    "topic": "打排位",
    "desc": "连跪中",
    "sign": "下",
    "fortune": "差",
    "probability": 0.3,
    "score": 3,
    "tip": "使用ThisAI换种思路上分！"
  },
  {
    "provider": "胡景浩",
    "topic": "巅峰赛",
    "desc": "金牌选手",
    "sign": "上",
    "fortune": "吉",
    "probability": 0.1,
    "score": 8,
    "tip": "使用ThisAI分享此刻心情！"
  },
  {
    "provider": "胡景浩",
    "topic": "带妹",
    "desc": "五连绝世",
    "sign": "上",
    "fortune": "吉",
    "probability": 0.015,
    "score": 9,
    "tip": "ThisAI教你飞雷神！"
  },
  {
    "provider": "胡景浩",
    "topic": "跑步",
    "desc": "烈日当空",
    "sign": "下",
    "fortune": "差",
    "probability": 0.1,
    "score": 4,
    "tip": "ThisAI为你记录努力！"
  },
  {
    "provider": "胡景浩",
    "topic": "抽卡",
    "desc": "小保底不歪",
    "sign": "上",
    "fortune": "吉",
    "probability": 0.02,
    "score": 8,
    "tip": "ThisAI助你一臂之力！"
  },
  {
    "provider": "胡景浩",
    "topic": "找野王哥哥",
    "desc": "躺赢",
    "sign": "中",
    "fortune": "吉",
    "probability": 0.15,
    "score": 6,
    "tip": "ThisAI教你如何撩野王！"
  },
  {
    "provider": "胡景浩",
    "topic": "打篮球",
    "desc": "三分雨",
    "sign": "上",
    "fortune": "吉",
    "probability": 0.05,
    "score": 7,
    "tip": "在ThisAI心中，你就是库里！"
  },
  {
    "provider": "胡景浩",
    "topic": "打篮球",
    "desc": "打铁达人",
    "sign": "下",
    "fortune": "差",
    "probability": 0.08,
    "score": 5,
    "tip": "What can I say！"
  },
  {
    "provider": "田正东",
    "topic": "辅导员dd",
    "desc": "事业新机遇，导员叫我去填表",
    "sign": "上",
    "fortune": "吉",
    "probability": 0.015,
    "score": 8,
    "tip": "使用ThisAI分析表格"
  },
  {
    "provider": "田正东",
    "topic": "发动态",
    "desc": "动态易发表，今天要发动态",
    "sign": "上",
    "fortune": "吉",
    "probability": 0.1,
    "score": 9,
    "tip": "让ThisAI帮你润色动态"
  },
  {
    "provider": "田正东",
    "topic": "买彩票",
    "desc": "彩票获利",
    "sign": "上",
    "fortune": "吉",
    "probability": 0.5,
    "score": 7,
    "tip": "ThisAI提供六合彩随机数给你"
  },
  {
    "provider": "田正东",
    "topic": "好姻缘",
    "desc": "心动不如行动，大胆才可能",
    "sign": "上",
    "fortune": "吉",
    "probability": 0.5,
    "score": 9,
    "tip": "ThisAI建议如何增进男女关系"
  },
  {
    "provider": "田正东",
    "topic": "要被导员教育",
    "desc": "如何让导员放过你",
    "sign": "上",
    "fortune": "吉",
    "probability": 0.1,
    "score": 8,
    "tip": "ThisAI提供柔性快熟通过难关"
  },
  {
    "provider": "田正东",
    "topic": "问候朋友",
    "desc": "朋友常相伴",
    "sign": "上",
    "fortune": "吉",
    "probability": 0.15,
    "score": 8,
    "tip": "ThisAI推荐增进友谊的方式"
  },
  {
    "provider": "田正东",
    "topic": "寝室生活",
    "desc": "物品怎么摆",
    "sign": "上",
    "fortune": "吉",
    "probability": 0.05,
    "score": 9,
    "tip": "ThisAI提供寝室居布置建议"
  },
  {
    "provider": "田正东",
    "topic": "艺术迸发",
    "desc": "今日灵感不断",
    "sign": "上",
    "fortune": "吉",
    "probability": 0.1,
    "score": 8,
    "tip": "ThisAI激发艺术创作灵感"
  },
  {
    "provider": "田正东",
    "topic": "交际",
    "desc": "人际交往顺畅",
    "sign": "上",
    "fortune": "吉",
    "probability": 0.2,
    "score": 7,
    "tip": "ThisAI教授有效沟通技巧"
  },
  {
    "provider": "田正东",
    "topic": "锻炼养生",
    "desc": "养生效果显著",
    "sign": "上",
    "fortune": "吉",
    "probability": 0.15,
    "score": 8,
    "tip": "ThisAI推荐科学养生方法"
  },
  {
    "provider": "谭卉苓",
    "topic": "宅家",
    "desc": "下雨天待在家，享受独处时间",
    "sign": "中",
    "fortune": "吉",
    "probability": 0.2,
    "score": 5,
    "tip": "让ThisAi来陪伴你！"
  },
  {
    "provider": "谭卉苓",
    "topic": "学习",
    "desc": "专注百分百",
    "sign": "上",
    "fortune": "吉",
    "probability": 0.5,
    "score": 8,
    "tip": "让ThisAi提高你的学习效率！"
  },
  {
    "provider": "谭卉苓",
    "topic": "抽卡",
    "desc": "欧气满满，一发中魂",
    "sign": "上",
    "fortune": "吉",
    "probability": 0.01,
    "score": 9,
    "tip": "用ThisAi助你一臂之力"
  },
  {
    "provider": "谭卉苓",
    "topic": "D牌",
    "desc": "三星五费，信手拈来",
    "sign": "上",
    "fortune": "吉",
    "probability": 0.01,
    "score": 9,
    "tip": "使用ThisAi查看攻略"
  },
  {
    "provider": "谭卉苓",
    "topic": "出行",
    "desc": "天气这么好，出门嗮嗮太阳",
    "sign": "上",
    "fortune": "吉",
    "probability": 0.5,
    "score": 5,
    "tip": "ThisAi带你寻找更好的风景"
  },
  {
    "provider": "谭卉苓",
    "topic": "煮饭",
    "desc": "建议清淡饮食",
    "sign": "中",
    "fortune": "差",
    "probability": 0.2,
    "score": 2,
    "tip": "This Ai为你推荐更适合的食谱"
  },
  {
    "provider": "谭卉苓",
    "topic": "跑步",
    "desc": "今天会下雨",
    "sign": "中",
    "fortune": "差",
    "probability": 0.2,
    "score": 3,
    "tip": "ThisAi为你保驾护航"
  },
  {
    "provider": "谭卉苓",
    "topic": "办公",
    "desc": "可以允许自己犯错",
    "sign": "下",
    "fortune": "差",
    "probability": 0.2,
    "score": 5,
    "tip": "ThisAi和你一起解决问题"
  },
  {
    "provider": "谭卉苓",
    "topic": "表白",
    "desc": "两情不相悦",
    "sign": "下",
    "fortune": "差",
    "probability": 0.2,
    "score": 5,
    "tip": "ThisAi和你一起看风景"
  },
  {
    "provider": "谭卉苓",
    "topic": "复合",
    "desc": "过去的就随风而去吧",
    "sign": "下",
    "fortune": "差",
    "probability": 0.2,
    "score": 5,
    "tip": "让ThisAi来帮你"
  },
  {
    "provider": "沈若瑄",
    "topic": "离婚",
    "desc": "或许自由更胜一筹",
    "sign": "下",
    "fortune": "差",
    "probability": 0.001,
    "score": 10,
    "tip": "咨询ThisAI需要什么证件！"
  },
  {
    "provider": "沈若瑄",
    "topic": "戒掉一天短视频",
    "desc": "放弃碎片化时间也许是一种收获",
    "sign": "中",
    "fortune": "下/中/上",
    "probability": 0.1,
    "score": 8,
    "tip": "使用ThisAI吸收不同领域前沿知识！"
  },
  {
    "provider": "沈若瑄",
    "topic": "去猫咖",
    "desc": "在毛孩子眼里，你是它们的全部",
    "sign": "上",
    "fortune": "吉",
    "probability": 0.1,
    "score": 7,
    "tip": "建议用ThisAI查查注意事项！"
  },
  {
    "provider": "沈若瑄",
    "topic": "找老同学聊聊天",
    "desc": "也许对方也在怀念从前",
    "sign": "上",
    "fortune": "下/中/上",
    "probability": 0.5,
    "score": 9,
    "tip": "用ThisAI开启不尴尬的聊天话术！"
  },
  {
    "provider": "沈若瑄",
    "topic": "使用This AI",
    "desc": "快速了解瞬息万变的世界",
    "sign": "上",
    "fortune": "下/中/上",
    "probability": 0.8,
    "score": 9,
    "tip": "ThisAI祝你顿悟！"
  },
  {
    "provider": "沈若瑄",
    "topic": "晒被子",
    "desc": "把螨虫杀光光",
    "sign": "中",
    "fortune": "差",
    "probability": 0.005,
    "score": 1,
    "tip": "ThisAI祝你被子香香！"
  },
  {
    "provider": "沈若瑄",
    "topic": "晒背",
    "desc": "祛湿，但要小心中暑哦",
    "sign": "中",
    "fortune": "下/中/上",
    "probability": 0.05,
    "score": 3,
    "tip": "ThisAI助你活力满满！"
  },
  {
    "provider": "沈若瑄",
    "topic": "复盘",
    "desc": "天天复盘，天天进步",
    "sign": "上",
    "fortune": "吉",
    "probability": 0.005,
    "score": 6,
    "tip": "ThisAI提供超多复盘模板"
  },
  {
    "provider": "沈若瑄",
    "topic": "看爽文",
    "desc": "可以看看《第一战场指挥官》哦~",
    "sign": "上",
    "fortune": "下/中/上",
    "probability": 0.5,
    "score": 7,
    "tip": "可以用ThisAI直接看简介哦"
  },
  {
    "provider": "沈若瑄",
    "topic": "断舍离",
    "desc": "断舍离能加强磁场能量哦~",
    "sign": "中",
    "fortune": "吉",
    "probability": 0.15,
    "score": 8,
    "tip": "问问ThisAI如何快速断舍离哦"
  },
  {
    "provider": "唐子贤",
    "topic": "出行",
    "desc": "一帆风顺吧",
    "sign": "下/中/上",
    "fortune": "吉",
    "probability": 0.1,
    "score": 6,
    "tip": "让ThisAI给你当规划师！"
  },
  {
    "provider": "唐子贤",
    "topic": "上课",
    "desc": "100%吸收",
    "sign": "下/中/上",
    "fortune": "吉",
    "probability": 0.1,
    "score": 6,
    "tip": "使用ThisAI吸收更彻底！"
  },
  {
    "provider": "唐子贤",
    "topic": "出行",
    "desc": "可能会下雨",
    "sign": "下/中/上",
    "fortune": "差",
    "probability": 0.1,
    "score": 2,
    "tip": "建议用ThisAI查查天气预报！"
  },
  {
    "provider": "唐子贤",
    "topic": "写代码",
    "desc": "敲敲代码，全是错误",
    "sign": "下",
    "fortune": "差",
    "probability": 0.05,
    "score": 1,
    "tip": "用ThisAI纠错，全部修复！"
  },
  {
    "provider": "唐子贤",
    "topic": "写代码",
    "desc": "0bug 0warning",
    "sign": "上",
    "fortune": "吉",
    "probability": 0.05,
    "score": 9,
    "tip": "ThisAI祝你思路如泉涌！"
  },
  {
    "provider": "唐子贤",
    "topic": "小镇做题家",
    "desc": "全部都AC",
    "sign": "上",
    "fortune": "吉",
    "probability": 0.005,
    "score": 10,
    "tip": "ThisAI祝你全过！"
  },
  {
    "provider": "唐子贤",
    "topic": "debug",
    "desc": "无所遁逃",
    "sign": "上",
    "fortune": "吉",
    "probability": 0.005,
    "score": 10,
    "tip": "ThisAI助你一臂之力！"
  },
  {
    "provider": "唐子贤",
    "topic": "debug",
    "desc": "一个也找不出来",
    "sign": "下",
    "fortune": "差",
    "probability": 0.005,
    "score": 0,
    "tip": "没关系，ThisAI来帮你！"
  },
  {
    "provider": "唐子贤",
    "topic": "走路",
    "desc": "倒霉到摔跤",
    "sign": "下",
    "fortune": "差",
    "probability": 0.005,
    "score": 0,
    "tip": "不要边走边用ThisAI哦！"
  },
  {
    "provider": "唐子贤",
    "topic": "休息",
    "desc": "放松一下会更好",
    "sign": "中/上",
    "fortune": "吉",
    "probability": 0.15,
    "score": 8,
    "tip": "问问ThisAI如何休息呢！"
  }
]